inventoryManagement/Inventory.py
inventoryManagement/Parts.py
inventoryManagement/Transaction.py
inventoryManagement/__init__.py
inventoryManagementFinalExam-0.1.dist-info/METADATA
inventoryManagementFinalExam-0.1.dist-info/WHEEL
inventoryManagementFinalExam-0.1.dist-info/top_level.txt
inventoryManagementFinalExam-0.1.dist-info/RECORD
